Workbook

Sheet Premissas
B3: Premissário | F3: 0 | G3: =F3+1 -> 1 | H3: =G3+1 -> 2 | I3: =H3+1 -> 3 | J3: =I3+1 -> 4 | K3: =J3+1 -> 5 | L3: =K3+1 -> 6 | M3: =L3+1 -> 7 | N3: =M3+1 -> 8 | ... Z3: =Y3+1 -> 20
B4: Dias/ano | C4: 365
B5: Inflação | C5: 0.04
B7: DRE
B9: Impostos
B10: PIS | C10: 0.0165
B11: COFINS | C11: 0.076
B12: ISS | C12: 0.05
B13: ICMS | C13: 0
B14: Imposto de Renda | C14: 0.34
B15: Compensação Prejuízo acumulado | C15: 0.3
B17: Volumes
B18: Produto 1 | C18: 100000
B19: Crescimento | F19: 0.05 | G19: 0.05 | H19: 0.05 | I19: 0.05 | J19: 0.05 | K19: 0.05 | L19: 0.05 | M19: 0.05 | N19: 0.05 | O19: 0.05 | P19: 0.05 | Q19: 0.05 | R19: 0.05 | S19: 0.05 | T19: 0.05 | U19: 0.05 | V19: 0.05 | W19: 0.05 | X19: 0.05 | Y19: 0.05 | Z19: 0.05
B20: Produto 2 | C20: 80000
B21: Crescimento | F21: 0.05 | G21: 0.05 | H21: 0.05 | I21: 0.05 | J21: 0.05 | K21: 0.05 | L21: 0.05 | M21: 0.05 | N21: 0.05 | O21: 0.05 | P21: 0.05 | Q21: 0.05 | R21: 0.05 | S21: 0.05 | T21: 0.05 | U21: 0.05 | V21: 0.05 | W21: 0.05 | X21: 0.05 | Y21: 0.05 | Z21: 0.05
B22: Produto 3 | C22: 75000
B23: Crescimento | F23: 0.05 | G23: 0.05 | H23: 0.05 | I23: 0.05 | J23: 0.05 | K23: 0.05 | L23: 0.05 | M23: 0.05 | N23: 0.05 | O23: 0.05 | P23: 0.05 | Q23: 0.05 | R23: 0.05 | S23: 0.05 | T23: 0.05 | U23: 0.05 | V23: 0.05 | W23: 0.05 | X23: 0.05 | Y23: 0.05 | Z23: 0.05
B24: Produto 4 | C24: 25000
B25: Crescimento | F25: 0.05 | G25: 0.05 | H25: 0.05 | I25: 0.05 | J25: 0.05 | K25: 0.05 | L25: 0.05 | M25: 0.05 | N25: 0.05 | O25: 0.05 | P25: 0.05 | Q25: 0.05 | R25: 0.05 | S25: 0.05 | T25: 0.05 | U25: 0.05 | V25: 0.05 | W25: 0.05 | X25: 0.05 | Y25: 0.05 | Z25: 0.05
B27: Receita
B28: Preço Produto 1 | C28: 60
B29: Preço Produto 2 | C29: 60
B30: Preço Produto 3 | C30: 60
B31: Preço Produto 4 | C31: 60
B33: Custos
B34: Custo Produto 1
B35: Fixo | C35: 1200000
B36: Variável | C36: 10
B37: Custo Produto 2
B38: Fixo | C38: 850000
B39: Variável | C39: 10
B40: Custo Produto 3
B41: Fixo | C41: 700000
B42: Variável | C42: 10
B43: Custo Produto 4
B44: Fixo | C44: 500000
B45: Variável | C45: 10
B47: SG&A
B48: Administrativo | C48: 3500000
B49: Comercial | C49: 2500000
B50: Outros | C50: 1000000
B52: Fluxo de Caixa
B54: Caixa Mínimo | C54: 1000000
B56: Investimentos
B58: CAPEX | F58: 20000000 | G58: 0 | H58: 0 | I58: 0 | J58: 0 | K58: 0 | L58: 0 | M58: 0 | N58: 0 | O58: 0 | P58: 0 | Q58: 0 | R58: 0 | S58: 0 | T58: 0 | U58: 0 | V58: 0 | W58: 0 | X58: 0 | Y58: 0 | Z58: 0
B59: Reinvestimento | C59: 0.05 | D59: invest. Inicial
B60: Vida útil | C60: 10 | D60: anos
B62: Dívida
B64: % CAPEX Financiado | C64: 0.7
B65: Vigência | C65: 7
B66: Carência principal | C66: 2
B67: Amortização | C67: =C65-C66 -> 5
B68: Carência juros | C68: 2
B69: Juros | C69: =((1+C70)*(1+C71))-1 -> 0.1024
B70: IPCA | C70: =C5 -> 0.04
B71: Spread | C71: 0.06
B73: WACC
B75: Ke (USD) = Rf + (Beta * (Rm-Rf)) + Rc | C75: =C76+(C79*(C77))+C80 -> 0.11296263
B76: Risk Free US | C76: 0.036
B77: Risk Premium (Rm-Rf) | C77: 0.06
B78: Beta Unlevered | C78: 0.71
B79: Beta Levered | C79: =C78*(1+(1-C89)*C93) -> 0.8660438
B80: Country Risk | C80: 0.025
B82: Long Term Inflation USD | C82: 0.02
B83: Long Term Inflation BR | C83: 0.035
B84: Inflation Differential | C84: =((1+C83)/(1+C82))-1 -> 0.014705882
B85: Ke BR | C85: =(1+C75)*(1+C84)-1 -> 0.12932973
B88: Kd | C88: =C69 -> 0.1024
B89: taxes | C89: =Premissas!C14 -> 0.34
B90: Kd (1-t) | C90: =C88*(1-C89) -> 0.067584
B93: D/(D+E) | C93: =1-C94 -> 0.333
B94: E/(D+E) | C94: 0.667
B96: WACC = (Ke*E/(D+E))+(Kd*(D/(D+E)) | C96: =(C85*C94)+(C90*C93) -> 0.1087684

Sheet DRE
F3: 0 | G3: =F3+1 -> 1 | H3: =G3+1 -> 2 | I3: =H3+1 -> 3 | J3: =I3+1 -> 4 | K3: =J3+1 -> 5 | L3: =K3+1 -> 6 | M3: =L3+1 -> 7 | N3: =M3+1 -> 8 | ... Z3: =Y3+1 -> 20
B5: Dias/ano | C5: =Premissas!C4 -> 365 | F5: =$C$5 -> 365 | G5: =$C$5 -> 365 | H5: =$C$5 -> 365 | I5: =$C$5 -> 365 | J5: =$C$5 -> 365 | K5: =$C$5 -> 365 | L5: =$C$5 -> 365 | M5: =$C$5 -> 365 | ... Z5: =$C$5 -> 365
B6: Inflação | C6: =Premissas!C5 -> 0.04 | F6: =(1+$C$6)^F3 -> 1 | G6: =(1+$C$6)^G3 -> 1.04 | H6: =(1+$C$6)^H3 -> 1.0816 | I6: =(1+$C$6)^I3 -> 1.124864 | J6: =(1+$C$6)^J3 -> 1.1698586 | K6: =(1+$C$6)^K3 -> 1.2166529 | L6: =(1+$C$6)^L3 -> 1.265319 | M6: =(1+$C$6)^M3 -> 1.3159318 | ... Z6: =(1+$C$6)^Z3 -> 2.1911231
B9: Volume/Operacional
B11: Produto 1 | C11: =Premissas!C18 -> 100000 | G11: =C11 -> 100000 | H11: =G11*(1+H12) -> 105000 | I11: =H11*(1+I12) -> 110250 | J11: =I11*(1+J12) -> 115762.5 | K11: =J11*(1+K12) -> 121550.62 | L11: =K11*(1+L12) -> 127628.16 | M11: =L11*(1+M12) -> 134009.56 | N11: =M11*(1+N12) -> 140710.04 | O11: =N11*(1+O12) -> 147745.54 | ... Z11: =Y11*(1+Z12) -> 252695.02
B12: Crescimento | G12: =Premissas!F19 -> 0.05 | H12: =Premissas!G19 -> 0.05 | I12: =Premissas!H19 -> 0.05 | J12: =Premissas!I19 -> 0.05 | K12: =Premissas!J19 -> 0.05 | L12: =Premissas!K19 -> 0.05 | M12: =Premissas!L19 -> 0.05 | N12: =Premissas!M19 -> 0.05 | ... Z12: =Premissas!Y19 -> 0.05
B13: Produto 2 | C13: =Premissas!C20 -> 80000 | G13: =C13 -> 80000 | H13: =G13*(1+H14) -> 84000 | I13: =H13*(1+I14) -> 88200 | J13: =I13*(1+J14) -> 92610 | K13: =J13*(1+K14) -> 97240.5 | L13: =K13*(1+L14) -> 102102.53 | M13: =L13*(1+M14) -> 107207.65 | N13: =M13*(1+N14) -> 112568.03 | O13: =N13*(1+O14) -> 118196.44 | ... Z13: =Y13*(1+Z14) -> 202156.02
B14: Crescimento | G14: =Premissas!F21 -> 0.05 | H14: =Premissas!G21 -> 0.05 | I14: =Premissas!H21 -> 0.05 | J14: =Premissas!I21 -> 0.05 | K14: =Premissas!J21 -> 0.05 | L14: =Premissas!K21 -> 0.05 | M14: =Premissas!L21 -> 0.05 | N14: =Premissas!M21 -> 0.05 | ... Z14: =Premissas!Y21 -> 0.05
B15: Produto 3 | C15: =Premissas!C22 -> 75000 | G15: =C15 -> 75000 | H15: =G15*(1+H16) -> 78750 | I15: =H15*(1+I16) -> 82687.5 | J15: =I15*(1+J16) -> 86821.875 | K15: =J15*(1+K16) -> 91162.969 | L15: =K15*(1+L16) -> 95721.117 | M15: =L15*(1+M16) -> 100507.17 | N15: =M15*(1+N16) -> 105532.53 | O15: =N15*(1+O16) -> 110809.16 | ... Z15: =Y15*(1+Z16) -> 189521.26
B16: Crescimento | G16: =Premissas!F23 -> 0.05 | H16: =Premissas!G23 -> 0.05 | I16: =Premissas!H23 -> 0.05 | J16: =Premissas!I23 -> 0.05 | K16: =Premissas!J23 -> 0.05 | L16: =Premissas!K23 -> 0.05 | M16: =Premissas!L23 -> 0.05 | N16: =Premissas!M23 -> 0.05 | ... Z16: =Premissas!Y23 -> 0.05
B17: Produto 4 | C17: =Premissas!C24 -> 25000 | G17: =C17 -> 25000 | H17: =G17*(1+H18) -> 26250 | I17: =H17*(1+I18) -> 27562.5 | J17: =I17*(1+J18) -> 28940.625 | K17: =J17*(1+K18) -> 30387.656 | L17: =K17*(1+L18) -> 31907.039 | M17: =L17*(1+M18) -> 33502.391 | N17: =M17*(1+N18) -> 35177.511 | O17: =N17*(1+O18) -> 36936.386 | ... Z17: =Y17*(1+Z18) -> 63173.755
B18: Crescimento | G18: =Premissas!F25 -> 0.05 | H18: =Premissas!G25 -> 0.05 | I18: =Premissas!H25 -> 0.05 | J18: =Premissas!I25 -> 0.05 | K18: =Premissas!J25 -> 0.05 | L18: =Premissas!K25 -> 0.05 | M18: =Premissas!L25 -> 0.05 | N18: =Premissas!M25 -> 0.05 | ... Z18: =Premissas!Y25 -> 0.05
B20: Preços
B22: Preço Produto 1 | F22: =Premissas!C28 -> 60 | G22: =F22*(1+$C$6) -> 62.4 | H22: =G22*(1+$C$6) -> 64.896 | I22: =H22*(1+$C$6) -> 67.49184 | J22: =I22*(1+$C$6) -> 70.191514 | K22: =J22*(1+$C$6) -> 72.999174 | L22: =K22*(1+$C$6) -> 75.919141 | M22: =L22*(1+$C$6) -> 78.955907 | N22: =M22*(1+$C$6) -> 82.114143 | ... Z22: =Y22*(1+$C$6) -> 131.46739
B23: Preço Produto 2 | F23: =Premissas!C29 -> 60 | G23: =F23*(1+$C$6) -> 62.4 | H23: =G23*(1+$C$6) -> 64.896 | I23: =H23*(1+$C$6) -> 67.49184 | J23: =I23*(1+$C$6) -> 70.191514 | K23: =J23*(1+$C$6) -> 72.999174 | L23: =K23*(1+$C$6) -> 75.919141 | M23: =L23*(1+$C$6) -> 78.955907 | N23: =M23*(1+$C$6) -> 82.114143 | ... Z23: =Y23*(1+$C$6) -> 131.46739
B24: Preço Produto 3 | F24: =Premissas!C30 -> 60 | G24: =F24*(1+$C$6) -> 62.4 | H24: =G24*(1+$C$6) -> 64.896 | I24: =H24*(1+$C$6) -> 67.49184 | J24: =I24*(1+$C$6) -> 70.191514 | K24: =J24*(1+$C$6) -> 72.999174 | L24: =K24*(1+$C$6) -> 75.919141 | M24: =L24*(1+$C$6) -> 78.955907 | N24: =M24*(1+$C$6) -> 82.114143 | ... Z24: =Y24*(1+$C$6) -> 131.46739
B25: Preço Produto 4 | F25: =Premissas!C31 -> 60 | G25: =F25*(1+$C$6) -> 62.4 | H25: =G25*(1+$C$6) -> 64.896 | I25: =H25*(1+$C$6) -> 67.49184 | J25: =I25*(1+$C$6) -> 70.191514 | K25: =J25*(1+$C$6) -> 72.999174 | L25: =K25*(1+$C$6) -> 75.919141 | M25: =L25*(1+$C$6) -> 78.955907 | N25: =M25*(1+$C$6) -> 82.114143 | ... Z25: =Y25*(1+$C$6) -> 131.46739
B27: Receita Bruta | F27: =SUM(F29:F32) -> 0 | G27: =SUM(G29:G32) -> 17472000 | H27: =SUM(H29:H32) -> 19079424 | I27: =SUM(I29:I32) -> 20834731 | J27: =SUM(J29:J32) -> 22751526 | K27: =SUM(K29:K32) -> 24844667 | L27: =SUM(L29:L32) -> 27130376 | M27: =SUM(M29:M32) -> 29626371 | ... Z27: =SUM(Z29:Z32) -> 93019232
B29: Receita Produto 1 | F29: =F11*F22 -> 0 | G29: =G11*G22 -> 6240000 | H29: =H11*H22 -> 6814080 | I29: =I11*I22 -> 7440975.4 | J29: =J11*J22 -> 8125545.1 | K29: =K11*K22 -> 8873095.2 | L29: =L11*L22 -> 9689420 | M29: =M11*M22 -> 10580847 | ... Z29: =Z11*Z22 -> 33221154
B30: Receita Produto 2 | F30: =F13*F23 -> 0 | G30: =G13*G23 -> 4992000 | H30: =H13*H23 -> 5451264 | I30: =I13*I23 -> 5952780.3 | J30: =J13*J23 -> 6500436.1 | K30: =K13*K23 -> 7098476.2 | L30: =L13*L23 -> 7751536 | M30: =M13*M23 -> 8464677.3 | ... Z30: =Z13*Z23 -> 26576923
B31: Receita Produto 3 | F31: =F15*F24 -> 0 | G31: =G15*G24 -> 4680000 | H31: =H15*H24 -> 5110560 | I31: =I15*I24 -> 5580731.5 | J31: =J15*J24 -> 6094158.8 | K31: =K15*K24 -> 6654821.4 | L31: =L15*L24 -> 7267065 | M31: =M15*M24 -> 7935635 | ... Z31: =Z15*Z24 -> 24915866
B32: Receita Produto 4 | F32: =F17*F25 -> 0 | G32: =G17*G25 -> 1560000 | H32: =H17*H25 -> 1703520 | I32: =I17*I25 -> 1860243.8 | J32: =J17*J25 -> 2031386.3 | K32: =K17*K25 -> 2218273.8 | L32: =L17*L25 -> 2422355 | M32: =M17*M25 -> 2645211.7 | ... Z32: =Z17*Z25 -> 8305288.6
B34: Impostos sobre Receita | F34: =SUM(F36:F39) -> 0 | G34: =SUM(G36:G39) -> -2489760 | H34: =SUM(H36:H39) -> -2718817.9 | I34: =SUM(I36:I39) -> -2968949.2 | J34: =SUM(J36:J39) -> -3242092.5 | K34: =SUM(K36:K39) -> -3540365 | L34: =SUM(L36:L39) -> -3866078.6 | M34: =SUM(M36:M39) -> -4221757.8 | ... Z34: =SUM(Z36:Z39) -> -13255241
B36: PIS | C36: =Premissas!C10 -> 0.0165 | F36: =F$27*-$C36 -> 0 | G36: =G$27*-$C36 -> -288288 | H36: =H$27*-$C36 -> -314810.5 | I36: =I$27*-$C36 -> -343773.06 | J36: =J$27*-$C36 -> -375400.18 | K36: =K$27*-$C36 -> -409937 | L36: =L$27*-$C36 -> -447651.2 | M36: =M$27*-$C36 -> -488835.11 | ... Z36: =Z$27*-$C36 -> -1534817.3
B37: COFINS | C37: =Premissas!C11 -> 0.076 | F37: =F$27*-$C37 -> 0 | G37: =G$27*-$C37 -> -1327872 | H37: =H$27*-$C37 -> -1450036.2 | I37: =I$27*-$C37 -> -1583439.6 | J37: =J$27*-$C37 -> -1729116 | K37: =K$27*-$C37 -> -1888194.7 | L37: =L$27*-$C37 -> -2061908.6 | M37: =M$27*-$C37 -> -2251604.2 | ... Z37: =Z$27*-$C37 -> -7069461.6
B38: ISS | C38: =Premissas!C12 -> 0.05 | F38: =F$27*-$C38 -> 0 | G38: =G$27*-$C38 -> -873600 | H38: =H$27*-$C38 -> -953971.2 | I38: =I$27*-$C38 -> -1041736.6 | J38: =J$27*-$C38 -> -1137576.3 | K38: =K$27*-$C38 -> -1242233.3 | L38: =L$27*-$C38 -> -1356518.8 | M38: =M$27*-$C38 -> -1481318.5 | ... Z38: =Z$27*-$C38 -> -4650961.6
B39: ICMS | C39: =Premissas!C13 -> 0 | F39: =F$27*-$C39 -> 0 | G39: =G$27*-$C39 -> 0 | H39: =H$27*-$C39 -> 0 | I39: =I$27*-$C39 -> 0 | J39: =J$27*-$C39 -> 0 | K39: =K$27*-$C39 -> 0 | L39: =L$27*-$C39 -> 0 | M39: =M$27*-$C39 -> 0 | ... Z39: =Z$27*-$C39 -> 0
B41: Receita Líquida | F41: =F27+F34 -> 0 | G41: =G27+G34 -> 14982240 | H41: =H27+H34 -> 16360606 | I41: =I27+I34 -> 17865782 | J41: =J27+J34 -> 19509434 | K41: =K27+K34 -> 21304302 | L41: =L27+L34 -> 23264297 | M41: =M27+M34 -> 25404613 | ... Z41: =Z27+Z34 -> 79763992
B43: Custos Operacionais | F43: =F45+F48+F51+F54 -> 0 | G43: =-(G45+G48+G51+G54) -> -6292000 | H43: =-(H45+H48+H51+H54) -> -6695104 | I43: =-(I45+I48+I51+I54) -> -7128263.2 | J43: =-(J45+J48+J51+J54) -> -7593961.4 | K43: =-(K45+K48+K51+K54) -> -8094899.7 | L43: =-(L45+L48+L51+L54) -> -8634016.1 | M43: =-(M45+M48+M51+M54) -> -9214506.7 | N43: =-(N45+N48+N51+N54) -> -9839848.9 | ... Z43: =-(Z45+Z48+Z51+Z54) -> -22624356
B45: Custo Produto 1 | G45: =SUM(G46:G47) -> 2288000 | H45: =SUM(H46:H47) -> 2433600 | I45: =SUM(I46:I47) -> 2589999.4 | J45: =SUM(J46:J47) -> 2758087.8 | K45: =SUM(K46:K47) -> 2938832.7 | L45: =SUM(L46:L47) -> 3133286.2 | M45: =SUM(M46:M47) -> 3342592.6 | N45: =SUM(N46:N47) -> 3567996.9 | ... Z45: =SUM(Z46:Z47) -> 8166206.8
B46: Fixo | C46: =Premissas!C35 -> 1200000 | G46: =$C46*G$6 -> 1248000 | H46: =$C46*H$6 -> 1297920 | I46: =$C46*I$6 -> 1349836.8 | J46: =$C46*J$6 -> 1403830.3 | K46: =$C46*K$6 -> 1459983.5 | L46: =$C46*L$6 -> 1518382.8 | M46: =$C46*M$6 -> 1579118.1 | N46: =$C46*N$6 -> 1642282.9 | ... Z46: =$C46*Z$6 -> 2629347.8
B47: Variável | C47: =Premissas!C36 -> 10 | G47: =G11*($C47*G$6) -> 1040000 | H47: =H11*($C47*H$6) -> 1135680 | I47: =I11*($C47*I$6) -> 1240162.6 | J47: =J11*($C47*J$6) -> 1354257.5 | K47: =K11*($C47*K$6) -> 1478849.2 | L47: =L11*($C47*L$6) -> 1614903.3 | M47: =M11*($C47*M$6) -> 1763474.4 | N47: =N11*($C47*N$6) -> 1925714.1 | ... Z47: =Z11*($C47*Z$6) -> 5536859.1
B48: Custo Produto 2 | G48: =SUM(G49:G50) -> 1716000 | H48: =SUM(H49:H50) -> 1827904 | I48: =SUM(I49:I50) -> 1948264.4 | J48: =SUM(J49:J50) -> 2077785.8 | K48: =SUM(K49:K50) -> 2217234.3 | L48: =SUM(L49:L50) -> 2367443.8 | M48: =SUM(M49:M50) -> 2529321.6 | N48: =SUM(N49:N50) -> 2703855 | ... Z48: =SUM(Z49:Z50) -> 6291941.9
B49: Fixo | C49: =Premissas!C38 -> 850000 | G49: =$C49*G$6 -> 884000 | H49: =$C49*H$6 -> 919360 | I49: =$C49*I$6 -> 956134.4 | J49: =$C49*J$6 -> 994379.78 | K49: =$C49*K$6 -> 1034155 | L49: =$C49*L$6 -> 1075521.2 | M49: =$C49*M$6 -> 1118542 | N49: =$C49*N$6 -> 1163283.7 | ... Z49: =$C49*Z$6 -> 1862454.7
B50: Variável | C50: =Premissas!C39 -> 10 | G50: =G13*($C50*G$6) -> 832000 | H50: =H13*($C50*H$6) -> 908544 | I50: =I13*($C50*I$6) -> 992130.05 | J50: =J13*($C50*J$6) -> 1083406 | K50: =K13*($C50*K$6) -> 1183079.4 | L50: =L13*($C50*L$6) -> 1291922.7 | M50: =M13*($C50*M$6) -> 1410779.6 | N50: =N13*($C50*N$6) -> 1540571.3 | ... Z50: =Z13*($C50*Z$6) -> 4429487.2
B51: Custo Produto 3 | G51: =SUM(G52:G53) -> 1508000 | H51: =SUM(H52:H53) -> 1608880 | I51: =SUM(I52:I53) -> 1717526.7 | J51: =SUM(J52:J53) -> 1834594.1 | K51: =SUM(K52:K53) -> 1960793.9 | L51: =SUM(L52:L53) -> 2096900.8 | M51: =SUM(M52:M53) -> 2243758.1 | N51: =SUM(N52:N53) -> 2402283.9 | ... Z51: =SUM(Z52:Z53) -> 5686430.5
B52: Fixo | C52: =Premissas!C41 -> 700000 | G52: =$C52*G$6 -> 728000 | H52: =$C52*H$6 -> 757120 | I52: =$C52*I$6 -> 787404.8 | J52: =$C52*J$6 -> 818900.99 | K52: =$C52*K$6 -> 851657.03 | L52: =$C52*L$6 -> 885723.31 | M52: =$C52*M$6 -> 921152.25 | N52: =$C52*N$6 -> 957998.34 | ... Z52: =$C52*Z$6 -> 1533786.2
B53: Variável | C53: =Premissas!C42 -> 10 | G53: =G15*($C53*G$6) -> 780000 | H53: =H15*($C53*H$6) -> 851760 | I53: =I15*($C53*I$6) -> 930121.92 | J53: =J15*($C53*J$6) -> 1015693.1 | K53: =K15*($C53*K$6) -> 1109136.9 | L53: =L15*($C53*L$6) -> 1211177.5 | M53: =M15*($C53*M$6) -> 1322605.8 | N53: =N15*($C53*N$6) -> 1444285.6 | ... Z53: =Z15*($C53*Z$6) -> 4152644.3
B54: Custo Produto 4 | G54: =SUM(G55:G56) -> 780000 | H54: =SUM(H55:H56) -> 824720 | I54: =SUM(I55:I56) -> 872472.64 | J54: =SUM(J55:J56) -> 923493.66 | K54: =SUM(K55:K56) -> 978038.75 | L54: =SUM(L55:L56) -> 1036385.3 | M54: =SUM(M55:M56) -> 1098834.5 | N54: =SUM(N55:N56) -> 1165713 | ... Z54: =SUM(Z55:Z56) -> 2479776.3
B55: Fixo | C55: =Premissas!C44 -> 500000 | G55: =$C55*G$6 -> 520000 | H55: =$C55*H$6 -> 540800 | I55: =$C55*I$6 -> 562432 | J55: =$C55*J$6 -> 584929.28 | K55: =$C55*K$6 -> 608326.45 | L55: =$C55*L$6 -> 632659.51 | M55: =$C55*M$6 -> 657965.89 | N55: =$C55*N$6 -> 684284.53 | ... Z55: =$C55*Z$6 -> 1095561.6
B56: Variável | C56: =Premissas!C45 -> 10 | G56: =G17*($C56*G$6) -> 260000 | H56: =H17*($C56*H$6) -> 283920 | I56: =I17*($C56*I$6) -> 310040.64 | J56: =J17*($C56*J$6) -> 338564.38 | K56: =K17*($C56*K$6) -> 369712.3 | L56: =L17*($C56*L$6) -> 403725.83 | M56: =M17*($C56*M$6) -> 440868.61 | N56: =N17*($C56*N$6) -> 481428.52 | ... Z56: =Z17*($C56*Z$6) -> 1384214.8
B58: Lucro Bruto | F58: =F41+F43 -> 0 | G58: =G41+G43 -> 8690240 | H58: =H41+H43 -> 9665502.1 | I58: =I41+I43 -> 10737519 | J58: =J41+J43 -> 11915472 | K58: =K41+K43 -> 13209402 | L58: =L41+L43 -> 14630281 | M58: =M41+M43 -> 16190106 | ... Z58: =Z41+Z43 -> 57139636
B60: SG&A | F60: =F62+F65+F68+F71 -> 0 | G60: =-SUM(G62:G64) -> -7280000 | H60: =-SUM(H62:H64) -> -7571200 | I60: =-SUM(I62:I64) -> -7874048 | J60: =-SUM(J62:J64) -> -8189009.9 | K60: =-SUM(K62:K64) -> -8516570.3 | L60: =-SUM(L62:L64) -> -8857233.1 | M60: =-SUM(M62:M64) -> -9211522.5 | N60: =-SUM(N62:N64) -> -9579983.4 | ... Z60: =-SUM(Z62:Z64) -> -15337862
B62: Administrativo | C62: =Premissas!C48 -> 3500000 | G62: =$C62*G$6 -> 3640000 | H62: =$C62*H$6 -> 3785600 | I62: =$C62*I$6 -> 3937024 | J62: =$C62*J$6 -> 4094505 | K62: =$C62*K$6 -> 4258285.2 | L62: =$C62*L$6 -> 4428616.6 | M62: =$C62*M$6 -> 4605761.2 | N62: =$C62*N$6 -> 4789991.7 | ... Z62: =$C62*Z$6 -> 7668931
B63: Comercial | C63: =Premissas!C49 -> 2500000 | G63: =$C63*G$6 -> 2600000 | H63: =$C63*H$6 -> 2704000 | I63: =$C63*I$6 -> 2812160 | J63: =$C63*J$6 -> 2924646.4 | K63: =$C63*K$6 -> 3041632.3 | L63: =$C63*L$6 -> 3163297.5 | M63: =$C63*M$6 -> 3289829.4 | N63: =$C63*N$6 -> 3421422.6 | ... Z63: =$C63*Z$6 -> 5477807.9
B64: Outros | C64: =Premissas!C50 -> 1000000 | G64: =$C64*G$6 -> 1040000 | H64: =$C64*H$6 -> 1081600 | I64: =$C64*I$6 -> 1124864 | J64: =$C64*J$6 -> 1169858.6 | K64: =$C64*K$6 -> 1216652.9 | L64: =$C64*L$6 -> 1265319 | M64: =$C64*M$6 -> 1315931.8 | N64: =$C64*N$6 -> 1368569.1 | ... Z64: =$C64*Z$6 -> 2191123.1
B66: EBITDA | F66: =F58+F60 -> 0 | G66: =G58+G60 -> 1410240 | H66: =H58+H60 -> 2094302.1 | I66: =I58+I60 -> 2863470.7 | J66: =J58+J60 -> 3726462.5 | K66: =K58+K60 -> 4692831.6 | L66: =L58+L60 -> 5773048.2 | M66: =M58+M60 -> 6978583.6 | ... Z66: =Z58+Z60 -> 41801774
B67: Margem EBITDA | G67: =G66/G41 -> 0.094127447 | H67: =H66/H41 -> 0.12800883 | I67: =I66/I41 -> 0.16027682 | J67: =J66/J41 -> 0.19100823 | K67: =K66/K41 -> 0.22027625 | L67: =L66/L41 -> 0.24815055 | M67: =M66/M41 -> 0.2746975 | N67: =N66/N41 -> 0.29998031 | ... Z67: =Z66/Z41 -> 0.52406823
B68: Depreciação/Amortização | F68: =Investimentos!F13 -> 0 | G68: =Investimentos!G13 -> -2000000 | H68: =Investimentos!H13 -> -2100000 | I68: =Investimentos!I13 -> -2200000 | J68: =Investimentos!J13 -> -2300000 | K68: =Investimentos!K13 -> -2400000 | L68: =Investimentos!L13 -> -2500000 | M68: =Investimentos!M13 -> -2600000 | ... Z68: =Investimentos!Z13 -> -1000000
B70: EBIT | F70: =F66+F68 -> 0 | G70: =G66+G68 -> -589760 | H70: =H66+H68 -> -5697.92 | I70: =I66+I68 -> 663470.67 | J70: =J66+J68 -> 1426462.5 | K70: =K66+K68 -> 2292831.6 | L70: =L66+L68 -> 3273048.2 | M70: =M66+M68 -> 4378583.6 | ... Z70: =Z66+Z68 -> 40801774
B72: Receita Financeira
B73: Despesa Financeira | F73: =-Dívida!F13 -> -716800 | G73: =-Dívida!G13 -> -1004666.9 | H73: =-Dívida!H13 -> -1073252.1 | I73: =-Dívida!I13 -> -858601.71 | J73: =-Dívida!J13 -> -643951.28 | K73: =-Dívida!K13 -> -429300.86 | L73: =-Dívida!L13 -> -214650.43 | M73: =-Dívida!M13 -> -1.847744e-10 | ... Z73: =-Dívida!Z13 -> -1.847744e-10
B75: EBT | F75: =F70+SUM(F72:F73) -> -716800 | G75: =G70+SUM(G72:G73) -> -1594426.9 | H75: =H70+SUM(H72:H73) -> -1078950.1 | I75: =I70+SUM(I72:I73) -> -195131.04 | J75: =J70+SUM(J72:J73) -> 782511.2 | K75: =K70+SUM(K72:K73) -> 1863530.8 | L75: =L70+SUM(L72:L73) -> 3058397.7 | M75: =M70+SUM(M72:M73) -> 4378583.6 | ... Z75: =Z70+SUM(Z72:Z73) -> 40801774
B77: Imposto de Renda | F77: =F103 -> 0 | G77: =G103 -> 0 | H77: =H103 -> 0 | I77: =I103 -> 0 | J77: =J103 -> -186237.67 | K77: =K103 -> -443520.33 | L77: =L103 -> -727898.66 | M77: =M103 -> -1042102.9 | ... Z77: =Z103 -> -13872603
B79: Resultado do Exercício | F79: =F75+F103 -> -716800 | G79: =G75+G103 -> -1594426.9 | H79: =H75+H103 -> -1078950.1 | I79: =I75+I103 -> -195131.04 | J79: =J75+J103 -> 596273.54 | K79: =K75+K103 -> 1420010.5 | L79: =L75+L103 -> 2330499.1 | M79: =M75+M103 -> 3336480.7 | ... Z79: =Z75+Z103 -> 26929171
B81: Resultado Acumulado
B83: Saldo Inicial | F83: 0 | G83: =F86 -> -473088 | H83: =G86 -> -1525409.7 | I83: =H86 -> -2237516.8 | J83: =I86 -> -2366303.3 | K83: =J86 -> -1849845.9 | L83: =K86 -> -619915.55 | M83: =L86 -> 1398626.9 | N83: =M86 -> 4288492.1 | ... Z83: =Y86 -> 1.5435553e+08
B84: EBT | F84: =F75 -> -716800 | G84: =G75 -> -1594426.9 | H84: =H75 -> -1078950.1 | I84: =I75 -> -195131.04 | J84: =J75 -> 782511.2 | K84: =K75 -> 1863530.8 | L84: =L75 -> 3058397.7 | M84: =M75 -> 4378583.6 | ... Z84: =Z75 -> 40801774
B85: Imposto de Renda | C85: =Premissas!$C$14 -> 0.34 | F85: =F84*-$C$85 -> 243712 | G85: =G84*-$C$85 -> 542105.14 | H85: =H84*-$C$85 -> 366843.02 | I85: =I84*-$C$85 -> 66344.554 | J85: =J84*-$C$85 -> -266053.81 | K85: =K84*-$C$85 -> -633600.47 | L85: =L84*-$C$85 -> -1039855.2 | M85: =M84*-$C$85 -> -1488718.4 | ... Z85: =Z84*-$C$85 -> -13872603
B86: Saldo Final | F86: =+SUM(F83:F85) -> -473088 | G86: =+SUM(G83:G85) -> -1525409.7 | H86: =+SUM(H83:H85) -> -2237516.8 | I86: =+SUM(I83:I85) -> -2366303.3 | J86: =+SUM(J83:J85) -> -1849845.9 | K86: =+SUM(K83:K85) -> -619915.55 | L86: =+SUM(L83:L85) -> 1398626.9 | M86: =+SUM(M83:M85) -> 4288492.1 | ... Z86: =+SUM(Z83:Z85) -> 1.812847e+08
B88: Ativo Fiscal Diferido
B90: Saldo Inicial | F90: 0 | G90: =F93 -> 243712 | H90: =G93 -> 785817.14 | I90: =H93 -> 1152660.2 | J90: =I93 -> 1219004.7 | K90: =J93 -> 1139188.6 | L90: =K93 -> 949108.43 | M90: =L93 -> 637151.86 | N90: =M93 -> 190536.33 | ... Z90: =Y93 -> 0
B91: (+) Adição | F91: =IF(F75<0,F75*-$C$103,0) -> 243712 | G91: =IF(G75<0,G75*-$C$103,0) -> 542105.14 | H91: =IF(H75<0,H75*-$C$103,0) -> 366843.02 | I91: =IF(I75<0,I75*-$C$103,0) -> 66344.554 | J91: =IF(J75<0,J75*-$C$103,0) -> 0 | K91: =IF(K75<0,K75*-$C$103,0) -> 0 | L91: =IF(L75<0,L75*-$C$103,0) -> 0 | M91: =IF(M75<0,M75*-$C$103,0) -> 0 | ... Z91: =IF(Z75<0,Z75*-$C$103,0) -> 0
B92: (-) Consumo | F92: =IF(F75<0,0,F75*-$C$103-F103) -> 0 | G92: =IF(G75<0,0,G75*-$C$103-G103) -> 0 | H92: =IF(H75<0,0,H75*-$C$103-H103) -> 0 | I92: =IF(I75<0,0,I75*-$C$103-I103) -> 0 | J92: =IF(J75<0,0,J75*-$C$103-J103) -> -79816.143 | K92: =IF(K75<0,0,K75*-$C$103-K103) -> -190080.14 | L92: =IF(L75<0,0,L75*-$C$103-L103) -> -311956.57 | M92: =IF(M75<0,0,M75*-$C$103-M103) -> -446615.53 | ... Z92: =IF(Z75<0,0,Z75*-$C$103-Z103) -> 0
B93: Saldo Final | F93: =SUM(F90:F92) -> 243712 | G93: =SUM(G90:G92) -> 785817.14 | H93: =SUM(H90:H92) -> 1152660.2 | I93: =SUM(I90:I92) -> 1219004.7 | J93: =SUM(J90:J92) -> 1139188.6 | K93: =SUM(K90:K92) -> 949108.43 | L93: =SUM(L90:L92) -> 637151.86 | M93: =SUM(M90:M92) -> 190536.33 | ... Z93: =SUM(Z90:Z92) -> 0
B95: Compensação Prejuízo acumulado
B97: Saldo Inicial | F97: 0 | G97: =F100 -> 716800 | H97: =G100 -> 2311226.9 | I97: =H100 -> 3390176.9 | J97: =I100 -> 3585308 | K97: =J100 -> 3350554.6 | L97: =K100 -> 2791495.4 | M97: =L100 -> 1873976.1 | N97: =M100 -> 560400.98
B98: (+) Adição | F98: =IF(F75<0,-F75,0) -> 716800 | G98: =IF(G75<0,-G75,0) -> 1594426.9 | H98: =IF(H75<0,-H75,0) -> 1078950.1 | I98: =IF(I75<0,-I75,0) -> 195131.04 | J98: =IF(J75<0,-J75,0) -> 0 | K98: =IF(K75<0,-K75,0) -> 0 | L98: =IF(L75<0,-L75,0) -> 0 | M98: =IF(M75<0,-M75,0) -> 0 | ... Z98: =IF(Z75<0,-Z75,0) -> 0
B99: (-) Compensação Prejuízo acumulado | C99: =Premissas!C15 -> 0.3 | F99: =IF(OR(F75<0,F90=0),0,MAX(F75*-$C$99,-F97)) -> 0 | G99: =IF(OR(G75<0,G90=0),0,MAX(G75*-$C$99,-G97)) -> 0 | H99: =IF(OR(H75<0,H90=0),0,MAX(H75*-$C$99,-H97)) -> 0 | I99: =IF(OR(I75<0,I90=0),0,MAX(I75*-$C$99,-I97)) -> 0 | J99: =IF(OR(J75<0,J90=0),0,MAX(J75*-$C$99,-J97)) -> -234753.36 | K99: =IF(OR(K75<0,K90=0),0,MAX(K75*-$C$99,-K97)) -> -559059.24 | L99: =IF(OR(L75<0,L90=0),0,MAX(L75*-$C$99,-L97)) -> -917519.32 | M99: =IF(OR(M75<0,M90=0),0,MAX(M75*-$C$99,-M97)) -> -1313575.1 | ... Z99: =IF(OR(Z75<0,Z90=0),0,MAX(Z75*-$C$99,-Z97)) -> 0
B100: Saldo Final | F100: =SUM(F97:F99) -> 716800 | G100: =SUM(G97:G99) -> 2311226.9 | H100: =SUM(H97:H99) -> 3390176.9 | I100: =SUM(I97:I99) -> 3585308 | J100: =SUM(J97:J99) -> 3350554.6 | K100: =SUM(K97:K99) -> 2791495.4 | L100: =SUM(L97:L99) -> 1873976.1 | M100: =SUM(M97:M99) -> 560400.98 | N100: =SUM(N97:N99) -> 0
B102: Nova Base tributos sobre Lucro | F102: =IF((F75+F99)<0,0,F75+F99) -> 0 | G102: =IF((G75+G99)<0,0,G75+G99) -> 0 | H102: =IF((H75+H99)<0,0,H75+H99) -> 0 | I102: =IF((I75+I99)<0,0,I75+I99) -> 0 | J102: =IF((J75+J99)<0,0,J75+J99) -> 547757.84 | K102: =IF((K75+K99)<0,0,K75+K99) -> 1304471.6 | L102: =IF((L75+L99)<0,0,L75+L99) -> 2140878.4 | M102: =IF((M75+M99)<0,0,M75+M99) -> 3065008.5 | ... Z102: =IF((Z75+Z99)<0,0,Z75+Z99) -> 40801774
B103: Imposto de Renda | C103: =Premissas!$C$14 -> 0.34 | F103: =IF(F75<0,0,F102*-$C103) -> 0 | G103: =IF(G75<0,0,G102*-$C103) -> 0 | H103: =IF(H75<0,0,H102*-$C103) -> 0 | I103: =IF(I75<0,0,I102*-$C103) -> 0 | J103: =IF(J75<0,0,J102*-$C103) -> -186237.67 | K103: =IF(K75<0,0,K102*-$C103) -> -443520.33 | L103: =IF(L75<0,0,L102*-$C103) -> -727898.66 | M103: =IF(M75<0,0,M102*-$C103) -> -1042102.9 | ... Z103: =IF(Z75<0,0,Z102*-$C103) -> -13872603

Sheet Balanço
F3: 0 | G3: =F3+1 -> 1 | H3: =G3+1 -> 2 | I3: =H3+1 -> 3 | J3: =I3+1 -> 4 | K3: =J3+1 -> 5 | L3: =K3+1 -> 6 | M3: =L3+1 -> 7 | N3: =M3+1 -> 8 | ... Z3: =Y3+1 -> 20
B5: Dias/ano | C5: =Premissas!$C$4 -> 365 | F5: =$C$5 -> 365 | G5: =$C$5 -> 365 | H5: =$C$5 -> 365 | I5: =$C$5 -> 365 | J5: =$C$5 -> 365 | K5: =$C$5 -> 365 | L5: =$C$5 -> 365 | M5: =$C$5 -> 365 | ... Z5: =$C$5 -> 365
B6: Inflação | C6: =Premissas!C5 -> 0.04 | F6: =(1+$C$6)^F3 -> 1 | G6: =(1+$C$6)^G3 -> 1.04 | H6: =(1+$C$6)^H3 -> 1.0816 | I6: =(1+$C$6)^I3 -> 1.124864 | J6: =(1+$C$6)^J3 -> 1.1698586 | K6: =(1+$C$6)^K3 -> 1.2166529 | L6: =(1+$C$6)^L3 -> 1.265319 | M6: =(1+$C$6)^M3 -> 1.3159318 | ... Z6: =(1+$C$6)^Z3 -> 2.1911231
B9: Ativo | F9: =SUM(F11:F15) -> 21243712 | G9: =SUM(G11:G15) -> 21270424 | H9: =SUM(H11:H15) -> 20442421 | I9: =SUM(I11:I15) -> 19341118 | J9: =SUM(J11:J15) -> 17996491 | K9: =SUM(K11:K15) -> 16444691 | L9: =SUM(L11:L15) -> 14674385 | M9: =SUM(M11:M15) -> 12673094 | ... Z9: =SUM(Z11:Z15) -> 8208127.8
B11: Caixa | F11: ='Fluxo de Caixa'!F33 -> 1000000 | G11: ='Fluxo de Caixa'!G33 -> 1124596.2 | H11: ='Fluxo de Caixa'!H33 -> 1000000 | I11: ='Fluxo de Caixa'!I33 -> 1000000 | J11: ='Fluxo de Caixa'!J33 -> 1000000 | K11: ='Fluxo de Caixa'!K33 -> 1000000 | L11: ='Fluxo de Caixa'!L33 -> 1000000 | M11: ='Fluxo de Caixa'!M33 -> 1000000 | ... Z11: ='Fluxo de Caixa'!Z33 -> 1000000
B12: Contas a Receber | F12: ='Capital de Giro'!F11 -> 0 | G12: ='Capital de Giro'!G11 -> 239342.47 | H12: ='Capital de Giro'!H11 -> 261361.97 | I12: ='Capital de Giro'!I11 -> 285407.27 | J12: ='Capital de Giro'!J11 -> 311664.74 | K12: ='Capital de Giro'!K11 -> 340337.9 | L12: ='Capital de Giro'!L11 -> 371648.99 | M12: ='Capital de Giro'!M11 -> 405840.69 | ... Z12: ='Capital de Giro'!Z11 -> 1274236.1
B13: Estoque | F13: ='Capital de Giro'!F12 -> 0 | G13: ='Capital de Giro'!G12 -> 120668.49 | H13: ='Capital de Giro'!H12 -> 128399.25 | I13: ='Capital de Giro'!I12 -> 136706.42 | J13: ='Capital de Giro'!J12 -> 145637.62 | K13: ='Capital de Giro'!K12 -> 155244.65 | L13: ='Capital de Giro'!L12 -> 165583.87 | M13: ='Capital de Giro'!M12 -> 176716.57 | ... Z13: ='Capital de Giro'!Z12 -> 433891.75
B14: Imposto Diferido | F14: =DRE!F93 -> 243712 | G14: =DRE!G93 -> 785817.14 | H14: =DRE!H93 -> 1152660.2 | I14: =DRE!I93 -> 1219004.7 | J14: =DRE!J93 -> 1139188.6 | K14: =DRE!K93 -> 949108.43 | L14: =DRE!L93 -> 637151.86 | M14: =DRE!M93 -> 190536.33 | ... Z14: =DRE!Z93 -> 0
B15: Imobilizado | F15: =Investimentos!F14 -> 20000000 | G15: =Investimentos!G14 -> 19000000 | H15: =Investimentos!H14 -> 17900000 | I15: =Investimentos!I14 -> 16700000 | J15: =Investimentos!J14 -> 15400000 | K15: =Investimentos!K14 -> 14000000 | L15: =Investimentos!L14 -> 12500000 | M15: =Investimentos!M14 -> 10900000 | ... Z15: =Investimentos!Z14 -> 5500000
B17: Passivo | F17: =SUM(F19:F20) -> 14716800 | G17: =SUM(G19:G20) -> 15795834 | H17: =SUM(H19:H20) -> 12655345 | I17: =SUM(I19:I20) -> 9515084.6 | J17: =SUM(J19:J20) -> 6375068.8 | K17: =SUM(K19:K20) -> 3235315.1 | L17: =SUM(L19:L20) -> 95842.462 | M17: =SUM(M19:M20) -> 100964.54 | ... Z17: =SUM(Z19:Z20) -> 208012.15
B19: Contas a Pagar | F19: ='Capital de Giro'!F13 -> 0 | G19: ='Capital de Giro'!G13 -> 74367.123 | H19: ='Capital de Giro'!H13 -> 78171.529 | I19: ='Capital de Giro'!I13 -> 82204.445 | J19: ='Capital de Giro'!J13 -> 86482.034 | K19: ='Capital de Giro'!K13 -> 91021.754 | L19: ='Capital de Giro'!L13 -> 95842.462 | M19: ='Capital de Giro'!M13 -> 100964.54 | ... Z19: ='Capital de Giro'!Z13 -> 208012.15
B20: Empréstimo | F20: =Dívida!F16 -> 14716800 | G20: =Dívida!G16 -> 15721467 | H20: =Dívida!H16 -> 12577174 | I20: =Dívida!I16 -> 9432880.1 | J20: =Dívida!J16 -> 6288586.8 | K20: =Dívida!K16 -> 3144293.4 | L20: =Dívida!L16 -> 2.7066562e-09 | M20: =Dívida!M16 -> 2.7066562e-09 | ... Z20: =Dívida!Z16 -> 2.7066562e-09
B22: PL | F22: =SUM(F24:F25) -> 6526912 | G22: =SUM(G24:G25) -> 5474590.3 | H22: =SUM(H24:H25) -> 7787076.4 | I22: =SUM(I24:I25) -> 9826033.8 | J22: =SUM(J24:J25) -> 11621422 | K22: =SUM(K24:K25) -> 13209376 | L22: =SUM(L24:L25) -> 15227918 | M22: =SUM(M24:M25) -> 18117784 | ... Z22: =SUM(Z24:Z25) -> 1.9511399e+08
B24: Resultado Acumulado | F24: =DRE!F86 -> -473088 | G24: =DRE!G86 -> -1525409.7 | H24: =DRE!H86 -> -2237516.8 | I24: =DRE!I86 -> -2366303.3 | J24: =DRE!J86 -> -1849845.9 | K24: =DRE!K86 -> -619915.55 | L24: =DRE!L86 -> 1398626.9 | M24: =DRE!M86 -> 4288492.1 | ... Z24: =DRE!Z86 -> 1.812847e+08
B25: Capital Solcial | F25: ='Fluxo de Caixa'!F40 -> 7000000 | G25: ='Fluxo de Caixa'!G40 -> 7000000 | H25: ='Fluxo de Caixa'!H40 -> 10024593 | I25: ='Fluxo de Caixa'!I40 -> 12192337 | J25: ='Fluxo de Caixa'!J40 -> 13471268 | K25: ='Fluxo de Caixa'!K40 -> 13829291 | L25: ='Fluxo de Caixa'!L40 -> 13829291 | M25: ='Fluxo de Caixa'!M40 -> 13829291 | ... Z25: ='Fluxo de Caixa'!Z40 -> 13829291
B28: Check | F28: =+F9-F17-F22 -> 0 | G28: =+G9-G17-G22 -> 0 | H28: =+H9-H17-H22 -> 0 | I28: =+I9-I17-I22 -> 0 | J28: =+J9-J17-J22 -> 0 | K28: =+K9-K17-K22 -> 0 | L28: =+L9-L17-L22 -> -649376.09 | M28: =+M9-M17-M22 -> -5545654.5 | ... Z28: =+Z9-Z17-Z22 -> -1.8711388e+08

Sheet Fluxo de Caixa
F3: 0 | G3: =F3+1 -> 1 | H3: =G3+1 -> 2 | I3: =H3+1 -> 3 | J3: =I3+1 -> 4 | K3: =J3+1 -> 5 | L3: =K3+1 -> 6 | M3: =L3+1 -> 7 | N3: =M3+1 -> 8 | ... Z3: =Y3+1 -> 20
B5: Dias/ano | C5: =Premissas!$C$4 -> 365 | F5: =$C$5 -> 365 | G5: =$C$5 -> 365 | H5: =$C$5 -> 365 | I5: =$C$5 -> 365 | J5: =$C$5 -> 365 | K5: =$C$5 -> 365 | L5: =$C$5 -> 365 | M5: =$C$5 -> 365 | ... Z5: =$C$5 -> 365
B6: Inflação | C6: =Premissas!C5 -> 0.04 | F6: =(1+$C$6)^F3 -> 1 | G6: =(1+$C$6)^G3 -> 1.04 | H6: =(1+$C$6)^H3 -> 1.0816 | I6: =(1+$C$6)^I3 -> 1.124864 | J6: =(1+$C$6)^J3 -> 1.1698586 | K6: =(1+$C$6)^K3 -> 1.2166529 | L6: =(1+$C$6)^L3 -> 1.265319 | M6: =(1+$C$6)^M3 -> 1.3159318 | ... Z6: =(1+$C$6)^Z3 -> 2.1911231
B9: Fluxo de Caixa Direto | F9: =F11+F20+F23 -> 1000000 | G9: =G11+G20+G23 -> 124596.16 | H9: =H11+H20+H23 -> -124596.16 | I9: =I11+I20+I23 -> 0 | J9: =J11+J20+J23 -> 0 | K9: =K11+K20+K23 -> 0 | L9: =L11+L20+L23 -> 0 | M9: =M11+M20+M23 -> 0 | ... Z9: =Z11+Z20+Z23 -> 0
B11: Fluxo de Caixa Operacional | F11: =SUM(F12:F18) -> 0 | G11: =SUM(G12:G18) -> 1124596.2 | H11: =SUM(H12:H18) -> 995104.08 | I11: =SUM(I12:I18) -> 1976549.4 | J11: =SUM(J12:J18) -> 2865362.5 | K11: =SUM(K12:K18) -> 3786270 | L11: =SUM(L12:L18) -> 4793669.5 | M11: =SUM(M12:M18) -> 5896278.4 | ... Z11: =SUM(Z12:Z18) -> 27803406
B12: (+) Resultado do Exercício | F12: =SUM(DRE!F84:F85) -> -473088 | G12: =SUM(DRE!G84:G85) -> -1052321.7 | H12: =SUM(DRE!H84:H85) -> -712107.04 | I12: =SUM(DRE!I84:I85) -> -128786.49 | J12: =SUM(DRE!J84:J85) -> 516457.39 | K12: =SUM(DRE!K84:K85) -> 1229930.3 | L12: =SUM(DRE!L84:L85) -> 2018542.5 | M12: =SUM(DRE!M84:M85) -> 2889865.2 | ... Z12: =SUM(DRE!Z84:Z85) -> 26929171
B13: (+) Imposto Diferido | F13: =-SUM(DRE!F91:F92) -> -243712 | G13: =-SUM(DRE!G91:G92) -> -542105.14 | H13: =-SUM(DRE!H91:H92) -> -366843.02 | I13: =-SUM(DRE!I91:I92) -> -66344.554 | J13: =-SUM(DRE!J91:J92) -> 79816.143 | K13: =-SUM(DRE!K91:K92) -> 190080.14 | L13: =-SUM(DRE!L91:L92) -> 311956.57 | M13: =-SUM(DRE!M91:M92) -> 446615.53 | ... Z13: =-SUM(DRE!Z91:Z92) -> 0
B14: (-) Contas a Receber | F14: =-'Capital de Giro'!F11 -> 0 | G14: =-'Capital de Giro'!G11+'Capital de Giro'!F11 -> -239342.47 | H14: =-'Capital de Giro'!H11+'Capital de Giro'!G11 -> -22019.507 | I14: =-'Capital de Giro'!I11+'Capital de Giro'!H11 -> -24045.301 | J14: =-'Capital de Giro'!J11+'Capital de Giro'!I11 -> -26257.469 | K14: =-'Capital de Giro'!K11+'Capital de Giro'!J11 -> -28673.156 | L14: =-'Capital de Giro'!L11+'Capital de Giro'!K11 -> -31311.087 | M14: =-'Capital de Giro'!M11+'Capital de Giro'!L11 -> -34191.707 | N14: =-'Capital de Giro'!N11+'Capital de Giro'!M11 -> -37337.344 | ... Z14: =-'Capital de Giro'!Z11+'Capital de Giro'!Y11 -> -107353.22
B15: (-) Estoque | F15: ='Capital de Giro'!F13 -> 0 | G15: =-'Capital de Giro'!G12+'Capital de Giro'!F12 -> -120668.49 | H15: =-'Capital de Giro'!H12+'Capital de Giro'!G12 -> -7730.7616 | I15: =-'Capital de Giro'!I12+'Capital de Giro'!H12 -> -8307.1621 | J15: =-'Capital de Giro'!J12+'Capital de Giro'!I12 -> -8931.1983 | K15: =-'Capital de Giro'!K12+'Capital de Giro'!J12 -> -9607.0368 | L15: =-'Capital de Giro'!L12+'Capital de Giro'!K12 -> -10339.219 | M15: =-'Capital de Giro'!M12+'Capital de Giro'!L12 -> -11132.696 | N15: =-'Capital de Giro'!N12+'Capital de Giro'!M12 -> -11992.863 | ... Z15: =-'Capital de Giro'!Z12+'Capital de Giro'!Y12 -> -30301.777
B16: (+) Contas a Pagar | F16: =+'Capital de Giro'!F13-'Capital de Giro'!E13 -> 0 | G16: =+'Capital de Giro'!G13-'Capital de Giro'!F13 -> 74367.123 | H16: =+'Capital de Giro'!H13-'Capital de Giro'!G13 -> 3804.4055 | I16: =+'Capital de Giro'!I13-'Capital de Giro'!H13 -> 4032.916 | J16: =+'Capital de Giro'!J13-'Capital de Giro'!I13 -> 4277.5897 | K16: =+'Capital de Giro'!K13-'Capital de Giro'!J13 -> 4539.7192 | L16: =+'Capital de Giro'!L13-'Capital de Giro'!K13 -> 4820.7082 | M16: =+'Capital de Giro'!M13-'Capital de Giro'!L13 -> 5122.0816 | ... Z16: =+'Capital de Giro'!Z13-'Capital de Giro'!Y13 -> 11890.077
B17: (-) Juros Incorridos não pagos | F17: =Dívida!F13+Dívida!F15 -> 716800 | G17: =Dívida!G13+Dívida!G15 -> 1004666.9 | H17: =Dívida!H13+Dívida!H15 -> 0 | I17: =Dívida!I13+Dívida!I15 -> 0 | J17: =Dívida!J13+Dívida!J15 -> 0 | K17: =Dívida!K13+Dívida!K15 -> 0 | L17: =Dívida!L13+Dívida!L15 -> 0 | M17: =Dívida!M13+Dívida!M15 -> 0 | ... Z17: =Dívida!Z13+Dívida!Z15 -> 0
B18: (+) Depreciação | F18: =-DRE!F68 -> 0 | G18: =-DRE!G68 -> 2000000 | H18: =-DRE!H68 -> 2100000 | I18: =-DRE!I68 -> 2200000 | J18: =-DRE!J68 -> 2300000 | K18: =-DRE!K68 -> 2400000 | L18: =-DRE!L68 -> 2500000 | M18: =-DRE!M68 -> 2600000 | ... Z18: =-DRE!Z68 -> 1000000
B20: Fluxo de Caixa de Investimentos | F20: =F21 -> -20000000 | G20: =G21 -> -1000000 | H20: =H21 -> -1000000 | I20: =I21 -> -1000000 | J20: =J21 -> -1000000 | K20: =K21 -> -1000000 | L20: =L21 -> -1000000 | M20: =M21 -> -1000000 | ... Z20: =Z21 -> -1000000
B21: (-) Investimentos | F21: =-Investimentos!F12 -> -20000000 | G21: =-Investimentos!G12 -> -1000000 | H21: =-Investimentos!H12 -> -1000000 | I21: =-Investimentos!I12 -> -1000000 | J21: =-Investimentos!J12 -> -1000000 | K21: =-Investimentos!K12 -> -1000000 | L21: =-Investimentos!L12 -> -1000000 | M21: =-Investimentos!M12 -> -1000000 | ... Z21: =-Investimentos!Z12 -> -1000000
B23: Fluxo de Caixa de Financiamentos | F23: =SUM(F24:F27) -> 21000000 | G23: =SUM(G24:G27) -> 0 | H23: =SUM(H24:H27) -> -119700.24 | I23: =SUM(I24:I27) -> -976549.41 | J23: =SUM(J24:J27) -> -1865362.5 | K23: =SUM(K24:K27) -> -2786270 | L23: =SUM(L24:L27) -> -3793669.5 | M23: =SUM(M24:M27) -> -4896278.4 | ... Z23: =SUM(Z24:Z27) -> -26803406
B24: (+) Captação Dívida | F24: =Dívida!F12 -> 14000000 | G24: =Dívida!G12 -> 0 | H24: =Dívida!H12 -> 0 | I24: =Dívida!I12 -> 0 | J24: =Dívida!J12 -> 0 | K24: =Dívida!K12 -> 0 | L24: =Dívida!L12 -> 0 | M24: =Dívida!M12 -> 0 | ... Z24: =Dívida!Z12 -> 0
B25: (-) Amortização Dívida | F25: =Dívida!F14 -> 0 | G25: =Dívida!G14 -> 0 | H25: =Dívida!H14 -> -3144293.4 | I25: =Dívida!I14 -> -3144293.4 | J25: =Dívida!J14 -> -3144293.4 | K25: =Dívida!K14 -> -3144293.4 | L25: =Dívida!L14 -> -3144293.4 | M25: =Dívida!M14 -> 0 | ... Z25: =Dívida!Z14 -> 0
B26: (+) Aporte de Capital | F26: =F35 -> 7000000 | G26: =G35 -> 0 | H26: =H35 -> 3024593.1 | I26: =I35 -> 2167744 | J26: =J35 -> 1278930.9 | K26: =K35 -> 358023.39 | L26: =L35 -> 0 | M26: =M35 -> 0 | ... Z26: =Z35 -> 0
B27: (-) Pagamento de Dividendos | F27: =-F42 -> 0 | G27: =-G42 -> 0 | H27: =-H42 -> 0 | I27: =-I42 -> 0 | J27: =-J42 -> 0 | K27: =-K42 -> 0 | L27: =-L42 -> -649376.09 | M27: =-M42 -> -4896278.4 | ... Z27: =-Z42 -> -26803406
B29: Saldo inicial | F29: 0 | G29: =F33 -> 1000000 | H29: =G33 -> 1124596.2 | I29: =H33 -> 1000000 | J29: =I33 -> 1000000 | K29: =J33 -> 1000000 | L29: =K33 -> 1000000 | M29: =L33 -> 1000000 | N29: =M33 -> 1000000 | ... Z29: =Y33 -> 1000000
B30: (+/-) Variação (ex aporte/dividendos) | F30: =+F11+F20+SUM(F24:F25) -> -6000000 | G30: =+G11+G20+SUM(G24:G25) -> 124596.16 | H30: =+H11+H20+SUM(H24:H25) -> -3149189.3 | I30: =+I11+I20+SUM(I24:I25) -> -2167744 | J30: =+J11+J20+SUM(J24:J25) -> -1278930.9 | K30: =+K11+K20+SUM(K24:K25) -> -358023.39 | L30: =+L11+L20+SUM(L24:L25) -> 649376.09 | M30: =+M11+M20+SUM(M24:M25) -> 4896278.4 | ... Z30: =+Z11+Z20+SUM(Z24:Z25) -> 26803406
B31: (+) Aporte de Capital | F31: =F26 -> 7000000 | G31: =G26 -> 0 | H31: =H26 -> 3024593.1 | I31: =I26 -> 2167744 | J31: =J26 -> 1278930.9 | K31: =K26 -> 358023.39 | L31: =L26 -> 0 | M31: =M26 -> 0 | ... Z31: =Z26 -> 0
B32: (-) Pagamento de Dividendos | F32: =F27 -> 0 | G32: =G27 -> 0 | H32: =H27 -> 0 | I32: =I27 -> 0 | J32: =J27 -> 0 | K32: =K27 -> 0 | L32: =L27 -> -649376.09 | M32: =M27 -> -4896278.4 | ... Z32: =Z27 -> -26803406
B33: Saldo Final | F33: =SUM(F29:F32) -> 1000000 | G33: =SUM(G29:G32) -> 1124596.2 | H33: =SUM(H29:H32) -> 1000000 | I33: =SUM(I29:I32) -> 1000000 | J33: =SUM(J29:J32) -> 1000000 | K33: =SUM(K29:K32) -> 1000000 | L33: =SUM(L29:L32) -> 1000000 | M33: =SUM(M29:M32) -> 1000000 | ... Z33: =SUM(Z29:Z32) -> 1000000
B35: Aporte de Capital | F35: =IF(SUM(F29:F30)<0-$C$36,-SUM(F29:F30)+$C$36,0) -> 7000000 | G35: =IF(SUM(G29:G30)<0++$C$36,-SUM(G29:G30)+$C$36,0) -> 0 | H35: =IF(SUM(H29:H30)<0++$C$36,-SUM(H29:H30)+$C$36,0) -> 3024593.1 | I35: =IF(SUM(I29:I30)<0++$C$36,-SUM(I29:I30)+$C$36,0) -> 2167744 | J35: =IF(SUM(J29:J30)<0++$C$36,-SUM(J29:J30)+$C$36,0) -> 1278930.9 | K35: =IF(SUM(K29:K30)<0++$C$36,-SUM(K29:K30)+$C$36,0) -> 358023.39 | L35: =IF(SUM(L29:L30)<0++$C$36,-SUM(L29:L30)+$C$36,0) -> 0 | M35: =IF(SUM(M29:M30)<0++$C$36,-SUM(M29:M30)+$C$36,0) -> 0 | N35: =IF(SUM(N29:N30)<0++$C$36,-SUM(N29:N30)+$C$36,0) -> 0 | ... Z35: =IF(SUM(Z29:Z30)<0++$C$36,-SUM(Z29:Z30)+$C$36,0) -> 0
B36: Caixa Mínimo | C36: =Premissas!C54 -> 1000000
B38: Saldo inicial Capital Social | F38: 0 | G38: =F40 -> 7000000 | H38: =G40 -> 7000000 | I38: =H40 -> 10024593 | J38: =I40 -> 12192337 | K38: =J40 -> 13471268 | L38: =K40 -> 13829291 | M38: =L40 -> 13829291 | N38: =M40 -> 13829291 | ... Z38: =Y40 -> 13829291
B39: (+) Adições | F39: =F35 -> 7000000 | G39: =G35 -> 0 | H39: =H35 -> 3024593.1 | I39: =I35 -> 2167744 | J39: =J35 -> 1278930.9 | K39: =K35 -> 358023.39 | L39: =L35 -> 0 | M39: =M35 -> 0 | ... Z39: =Z35 -> 0
B40: Saldo final Capital Social | F40: =SUM(F38:F39) -> 7000000 | G40: =SUM(G38:G39) -> 7000000 | H40: =SUM(H38:H39) -> 10024593 | I40: =SUM(I38:I39) -> 12192337 | J40: =SUM(J38:J39) -> 13471268 | K40: =SUM(K38:K39) -> 13829291 | L40: =SUM(L38:L39) -> 13829291 | M40: =SUM(M38:M39) -> 13829291 | ... Z40: =SUM(Z38:Z39) -> 13829291
B42: Pagamento Dividendos | F42: =IF(F43<0,0,IF(SUM(F29:F31)<$C$36,0,IF(SUM(F29:F31)>$C$36,SUM(F29:F31)-$C$36))) -> 0 | G42: =IF(G43<0,0,IF(SUM(G29:G31)<$C$36,0,IF(SUM(G29:G31)>$C$36,SUM(G29:G31)-$C$36))) -> 0 | H42: =IF(H43<0,0,IF(SUM(H29:H31)<$C$36,0,IF(SUM(H29:H31)>$C$36,SUM(H29:H31)-$C$36))) -> 0 | I42: =IF(I43<0,0,IF(SUM(I29:I31)<$C$36,0,IF(SUM(I29:I31)>$C$36,SUM(I29:I31)-$C$36))) -> 0 | J42: =IF(J43<0,0,IF(SUM(J29:J31)<$C$36,0,IF(SUM(J29:J31)>$C$36,SUM(J29:J31)-$C$36))) -> 0 | K42: =IF(K43<0,0,IF(SUM(K29:K31)<$C$36,0,IF(SUM(K29:K31)>$C$36,SUM(K29:K31)-$C$36))) -> 0 | L42: =IF(L43<0,0,IF(SUM(L29:L31)<$C$36,0,IF(SUM(L29:L31)>$C$36,SUM(L29:L31)-$C$36))) -> 649376.09 | M42: =IF(M43<0,0,IF(SUM(M29:M31)<$C$36,0,IF(SUM(M29:M31)>$C$36,SUM(M29:M31)-$C$36))) -> 4896278.4 | ... Z42: =IF(Z43<0,0,IF(SUM(Z29:Z31)<$C$36,0,IF(SUM(Z29:Z31)>$C$36,SUM(Z29:Z31)-$C$36))) -> 26803406
B43: Resultado Acumulado | F43: =DRE!F86 -> -473088 | G43: =DRE!G86 -> -1525409.7 | H43: =DRE!H86 -> -2237516.8 | I43: =DRE!I86 -> -2366303.3 | J43: =DRE!J86 -> -1849845.9 | K43: =DRE!K86 -> -619915.55 | L43: =DRE!L86 -> 1398626.9 | M43: =DRE!M86 -> 4288492.1 | ... Z43: =DRE!Z86 -> 1.812847e+08
B45: FFCF
B47: EBIT | F47: =DRE!F70 -> 0 | G47: =DRE!G70 -> -589760 | H47: =DRE!H70 -> -5697.92 | I47: =DRE!I70 -> 663470.67 | J47: =DRE!J70 -> 1426462.5 | K47: =DRE!K70 -> 2292831.6 | L47: =DRE!L70 -> 3273048.2 | M47: =DRE!M70 -> 4378583.6 | ... Z47: =DRE!Z70 -> 40801774
B48: Impostos | C48: =Premissas!$C$14 -> 0.34 | F48: =F47*-$C$48 -> 0 | G48: =G47*-$C$48 -> 200518.4 | H48: =H47*-$C$48 -> 1937.2928 | I48: =I47*-$C$48 -> -225580.03 | J48: =J47*-$C$48 -> -484997.24 | K48: =K47*-$C$48 -> -779562.76 | L48: =L47*-$C$48 -> -1112836.4 | M48: =M47*-$C$48 -> -1488718.4 | ... Z48: =Z47*-$C$48 -> -13872603
B49: NOPAT | F49: =SUM(F47:F48) -> 0 | G49: =SUM(G47:G48) -> -389241.6 | H49: =SUM(H47:H48) -> -3760.6272 | I49: =SUM(I47:I48) -> 437890.64 | J49: =SUM(J47:J48) -> 941465.24 | K49: =SUM(K47:K48) -> 1513268.9 | L49: =SUM(L47:L48) -> 2160211.8 | M49: =SUM(M47:M48) -> 2889865.2 | ... Z49: =SUM(Z47:Z48) -> 26929171
B50: (-) Investimentos | F50: =-Investimentos!F12 -> -20000000 | G50: =-Investimentos!G12 -> -1000000 | H50: =-Investimentos!H12 -> -1000000 | I50: =-Investimentos!I12 -> -1000000 | J50: =-Investimentos!J12 -> -1000000 | K50: =-Investimentos!K12 -> -1000000 | L50: =-Investimentos!L12 -> -1000000 | M50: =-Investimentos!M12 -> -1000000 | ... Z50: =-Investimentos!Z12 -> -1000000
B51: (+) Depreciação | F51: =-DRE!F68 -> 0 | G51: =-DRE!G68 -> 2000000 | H51: =-DRE!H68 -> 2100000 | I51: =-DRE!I68 -> 2200000 | J51: =-DRE!J68 -> 2300000 | K51: =-DRE!K68 -> 2400000 | L51: =-DRE!L68 -> 2500000 | M51: =-DRE!M68 -> 2600000 | ... Z51: =-DRE!Z68 -> 1000000
B52: (+/-) Var. Capital de Giro | F52: ='Capital de Giro'!F14 -> 0 | G52: ='Capital de Giro'!G14 -> -285643.84 | H52: ='Capital de Giro'!H14 -> -25945.863 | I52: ='Capital de Giro'!I14 -> -28319.548 | J52: ='Capital de Giro'!J14 -> -30911.078 | K52: ='Capital de Giro'!K14 -> -33740.474 | L52: ='Capital de Giro'!L14 -> -36829.598 | M52: ='Capital de Giro'!M14 -> -40202.321 | ... Z52: ='Capital de Giro'!Z14 -> -125764.92
B53: FFCF | F53: =SUM(F49:F52) -> -20000000 | G53: =SUM(G49:G52) -> 325114.56 | H53: =SUM(H49:H52) -> 1070293.5 | I53: =SUM(I49:I52) -> 1609571.1 | J53: =SUM(J49:J52) -> 2210554.2 | K53: =SUM(K49:K52) -> 2879528.4 | L53: =SUM(L49:L52) -> 3623382.2 | M53: =SUM(M49:M52) -> 4449662.9 | ... Z53: =SUM(Z49:Z52) -> 26803406
B55: VPL | C55: =NPV(C56,G53:Z53)+F53 -> 27775273
B56: WACC | C56: =Premissas!C96 -> 0.1087684
B57: TIR | C57: =IRR(F53:Z53) -> 0.19626503
B60: FFCE
B62: Lucro Líquido | F62: =DRE!F79 -> -716800 | G62: =DRE!G79 -> -1594426.9 | H62: =DRE!H79 -> -1078950.1 | I62: =DRE!I79 -> -195131.04 | J62: =DRE!J79 -> 596273.54 | K62: =DRE!K79 -> 1420010.5 | L62: =DRE!L79 -> 2330499.1 | M62: =DRE!M79 -> 3336480.7 | ... Z62: =DRE!Z79 -> 26929171
B63: (-) Investimentos | F63: =-Investimentos!F12 -> -20000000 | G63: =-Investimentos!G12 -> -1000000 | H63: =-Investimentos!H12 -> -1000000 | I63: =-Investimentos!I12 -> -1000000 | J63: =-Investimentos!J12 -> -1000000 | K63: =-Investimentos!K12 -> -1000000 | L63: =-Investimentos!L12 -> -1000000 | M63: =-Investimentos!M12 -> -1000000 | ... Z63: =-Investimentos!Z12 -> -1000000
B64: (+) Depreciação | F64: =-DRE!F68 -> 0 | G64: =-DRE!G68 -> 2000000 | H64: =-DRE!H68 -> 2100000 | I64: =-DRE!I68 -> 2200000 | J64: =-DRE!J68 -> 2300000 | K64: =-DRE!K68 -> 2400000 | L64: =-DRE!L68 -> 2500000 | M64: =-DRE!M68 -> 2600000 | ... Z64: =-DRE!Z68 -> 1000000
B65: (-) Fluxo Caixa Dívida | F65: =SUM(F24:F25) -> 14000000 | G65: =SUM(G24:G25) -> 0 | H65: =SUM(H24:H25) -> -3144293.4 | I65: =SUM(I24:I25) -> -3144293.4 | J65: =SUM(J24:J25) -> -3144293.4 | K65: =SUM(K24:K25) -> -3144293.4 | L65: =SUM(L24:L25) -> -3144293.4 | M65: =SUM(M24:M25) -> 0 | ... Z65: =SUM(Z24:Z25) -> 0
B66: (+/-) Var. Capital de Giro | F66: ='Capital de Giro'!F14+F17 -> 716800 | G66: ='Capital de Giro'!G14+G17 -> 719023.04 | H66: ='Capital de Giro'!H14+H17 -> -25945.863 | I66: ='Capital de Giro'!I14+I17 -> -28319.548 | J66: ='Capital de Giro'!J14+J17 -> -30911.078 | K66: ='Capital de Giro'!K14+K17 -> -33740.474 | L66: ='Capital de Giro'!L14+L17 -> -36829.598 | M66: ='Capital de Giro'!M14+M17 -> -40202.321 | ... Z66: ='Capital de Giro'!Z14+Z17 -> -125764.92
B68: FFCE | F68: =SUM(F62:F66) -> -6000000 | G68: =SUM(G62:G66) -> 124596.16 | H68: =SUM(H62:H66) -> -3149189.3 | I68: =SUM(I62:I66) -> -2167744 | J68: =SUM(J62:J66) -> -1278930.9 | K68: =SUM(K62:K66) -> -358023.39 | L68: =SUM(L62:L66) -> 649376.09 | M68: =SUM(M62:M66) -> 4896278.4 | ... Z68: =SUM(Z62:Z66) -> 26803406
B70: VPL | C70: =NPV(C71,G68:Z68)+F68 -> 20962926
B71: Ke | C71: =Premissas!C85 -> 0.12932973
B72: TIR | C72: =IRR(F68:Z68) -> 0.23814656

Sheet Investimentos
F3: 0 | G3: =F3+1 -> 1 | H3: =G3+1 -> 2 | I3: =H3+1 -> 3 | J3: =I3+1 -> 4 | K3: =J3+1 -> 5 | L3: =K3+1 -> 6 | M3: =L3+1 -> 7 | N3: =M3+1 -> 8 | ... Z3: =Y3+1 -> 20
B5: Dias/ano | C5: =Premissas!$C$4 -> 365 | F5: =$C$5 -> 365 | G5: =$C$5 -> 365 | H5: =$C$5 -> 365 | I5: =$C$5 -> 365 | J5: =$C$5 -> 365 | K5: =$C$5 -> 365 | L5: =$C$5 -> 365 | M5: =$C$5 -> 365 | ... Z5: =$C$5 -> 365
B6: Inflação | C6: =Premissas!C5 -> 0.04 | F6: =(1+$C$6)^F3 -> 1 | G6: =(1+$C$6)^G3 -> 1.04 | H6: =(1+$C$6)^H3 -> 1.0816 | I6: =(1+$C$6)^I3 -> 1.124864 | J6: =(1+$C$6)^J3 -> 1.1698586 | K6: =(1+$C$6)^K3 -> 1.2166529 | L6: =(1+$C$6)^L3 -> 1.265319 | M6: =(1+$C$6)^M3 -> 1.3159318 | ... Z6: =(1+$C$6)^Z3 -> 2.1911231
B9: Saldo Imobilizado
B11: Saldo Inicial | F11: 0 | G11: =F14 -> 20000000 | H11: =G14 -> 19000000 | I11: =H14 -> 17900000 | J11: =I14 -> 16700000 | K11: =J14 -> 15400000 | L11: =K14 -> 14000000 | M11: =L14 -> 12500000 | N11: =M14 -> 10900000 | ... Z11: =Y14 -> 5500000
B12: (+) Adições | F12: =F17+F23 -> 20000000 | G12: =G17+G23 -> 1000000 | H12: =H17+H23 -> 1000000 | I12: =I17+I23 -> 1000000 | J12: =J17+J23 -> 1000000 | K12: =K17+K23 -> 1000000 | L12: =L17+L23 -> 1000000 | M12: =M17+M23 -> 1000000 | ... Z12: =Z17+Z23 -> 1000000
B13: (-) Depreciação | F13: =F18+F24 -> 0 | G13: =G18+G24 -> -2000000 | H13: =H18+H24 -> -2100000 | I13: =I18+I24 -> -2200000 | J13: =J18+J24 -> -2300000 | K13: =K18+K24 -> -2400000 | L13: =L18+L24 -> -2500000 | M13: =M18+M24 -> -2600000 | ... Z13: =Z18+Z24 -> -1000000
B14: Saldo Final | F14: =SUM(F11:F13) -> 20000000 | G14: =SUM(G11:G13) -> 19000000 | H14: =SUM(H11:H13) -> 17900000 | I14: =SUM(I11:I13) -> 16700000 | J14: =SUM(J11:J13) -> 15400000 | K14: =SUM(K11:K13) -> 14000000 | L14: =SUM(L11:L13) -> 12500000 | M14: =SUM(M11:M13) -> 10900000 | ... Z14: =SUM(Z11:Z13) -> 5500000
B16: Novos Investimentos
B17: Adição | F17: =Premissas!F58 -> 20000000
B18: Depreciação | C18: =1/C19 -> 0.1 | G18: =-$C$18*SUM(OFFSET(F17,0,0,,-MIN(G3-$F$3,$C$19))) -> -2000000 | H18: =-$C$18*SUM(OFFSET(G17,0,0,,-MIN(H3-$F$3,$C$19))) -> -2000000 | I18: =-$C$18*SUM(OFFSET(H17,0,0,,-MIN(I3-$F$3,$C$19))) -> -2000000 | J18: =-$C$18*SUM(OFFSET(I17,0,0,,-MIN(J3-$F$3,$C$19))) -> -2000000 | K18: =-$C$18*SUM(OFFSET(J17,0,0,,-MIN(K3-$F$3,$C$19))) -> -2000000 | L18: =-$C$18*SUM(OFFSET(K17,0,0,,-MIN(L3-$F$3,$C$19))) -> -2000000 | M18: =-$C$18*SUM(OFFSET(L17,0,0,,-MIN(M3-$F$3,$C$19))) -> -2000000 | N18: =-$C$18*SUM(OFFSET(M17,0,0,,-MIN(N3-$F$3,$C$19))) -> -2000000 | ... Z18: =-$C$18*SUM(OFFSET(Y17,0,0,,-MIN(Z3-$F$3,$C$19))) -> 0
B19: Vida útil | C19: =Premissas!$C$60 -> 10 | D19: anos
B22: Reinvestimento
B23: Adição | C23: =Premissas!$C$59 -> 0.05 | D23: invest. Inicial | G23: =SUM($F$17:G17)*$C$23 -> 1000000 | H23: =SUM($F$17:H17)*$C$23 -> 1000000 | I23: =SUM($F$17:I17)*$C$23 -> 1000000 | J23: =SUM($F$17:J17)*$C$23 -> 1000000 | K23: =SUM($F$17:K17)*$C$23 -> 1000000 | L23: =SUM($F$17:L17)*$C$23 -> 1000000 | M23: =SUM($F$17:M17)*$C$23 -> 1000000 | N23: =SUM($F$17:N17)*$C$23 -> 1000000 | ... Z23: =SUM($F$17:Z17)*$C$23 -> 1000000
B24: Depreciação | C24: =1/C25 -> 0.1 | G24: =-$C$24*SUM(OFFSET(F23,0,0,,-MIN(G3-$F$3,$C$25))) -> 0 | H24: =-$C$24*SUM(OFFSET(G23,0,0,,-MIN(H3-$F$3,$C$25))) -> -100000 | I24: =-$C$24*SUM(OFFSET(H23,0,0,,-MIN(I3-$F$3,$C$25))) -> -200000 | J24: =-$C$24*SUM(OFFSET(I23,0,0,,-MIN(J3-$F$3,$C$25))) -> -300000 | K24: =-$C$24*SUM(OFFSET(J23,0,0,,-MIN(K3-$F$3,$C$25))) -> -400000 | L24: =-$C$24*SUM(OFFSET(K23,0,0,,-MIN(L3-$F$3,$C$25))) -> -500000 | M24: =-$C$24*SUM(OFFSET(L23,0,0,,-MIN(M3-$F$3,$C$25))) -> -600000 | N24: =-$C$24*SUM(OFFSET(M23,0,0,,-MIN(N3-$F$3,$C$25))) -> -700000 | ... Z24: =-$C$24*SUM(OFFSET(Y23,0,0,,-MIN(Z3-$F$3,$C$25))) -> -1000000
B25: Vida útil | C25: =Premissas!$C$60 -> 10 | D25: anos

Sheet Dívida
F3: 0 | G3: =F3+1 -> 1 | H3: =G3+1 -> 2 | I3: =H3+1 -> 3 | J3: =I3+1 -> 4 | K3: =J3+1 -> 5 | L3: =K3+1 -> 6 | M3: =L3+1 -> 7 | N3: =M3+1 -> 8 | ... Z3: =Y3+1 -> 20
B5: Dias/ano | C5: =Premissas!$C$4 -> 365 | F5: =$C$5 -> 365 | G5: =$C$5 -> 365 | H5: =$C$5 -> 365 | I5: =$C$5 -> 365 | J5: =$C$5 -> 365 | K5: =$C$5 -> 365 | L5: =$C$5 -> 365 | M5: =$C$5 -> 365 | ... Z5: =$C$5 -> 365
B6: Inflação | C6: =Premissas!C5 -> 0.04 | F6: =(1+$C$6)^F3 -> 1 | G6: =(1+$C$6)^G3 -> 1.04 | H6: =(1+$C$6)^H3 -> 1.0816 | I6: =(1+$C$6)^I3 -> 1.124864 | J6: =(1+$C$6)^J3 -> 1.1698586 | K6: =(1+$C$6)^K3 -> 1.2166529 | L6: =(1+$C$6)^L3 -> 1.265319 | M6: =(1+$C$6)^M3 -> 1.3159318 | ... Z6: =(1+$C$6)^Z3 -> 2.1911231
B9: Saldo Empréstimos
B11: Saldo Inicial | F11: 0 | G11: =F16 -> 14716800 | H11: =G16 -> 15721467 | I11: =H16 -> 12577174 | J11: =I16 -> 9432880.1 | K11: =J16 -> 6288586.8 | L11: =K16 -> 3144293.4 | M11: =L16 -> 2.7066562e-09 | N11: =M16 -> 2.7066562e-09 | ... Z11: =Y16 -> 2.7066562e-09
B12: (+) Adições | F12: =F20 -> 14000000 | G12: =G20 -> 0 | H12: =H20 -> 0 | I12: =I20 -> 0 | J12: =J20 -> 0 | K12: =K20 -> 0 | L12: =L20 -> 0 | M12: =M20 -> 0 | ... Z12: =Z20 -> 0
B13: (+) Juros Incorridos | F13: =F27 -> 716800 | G13: =G27 -> 1004666.9 | H13: =H27 -> 1073252.1 | I13: =I27 -> 858601.71 | J13: =J27 -> 643951.28 | K13: =K27 -> 429300.86 | L13: =L27 -> 214650.43 | M13: =M27 -> 1.847744e-10 | ... Z13: =Z27 -> 1.847744e-10
B14: (-) Amortização | F14: =+F24 -> 0 | G14: =+G24 -> 0 | H14: =+H24 -> -3144293.4 | I14: =+I24 -> -3144293.4 | J14: =+J24 -> -3144293.4 | K14: =+K24 -> -3144293.4 | L14: =+L24 -> -3144293.4 | M14: =+M24 -> 0 | ... Z14: =+Z24 -> 0
B15: (-) Pagamento Juros | F15: =IF(F3<$C$25,0,-F27) -> 0 | G15: =IF(G3<$C$25,0,-G27) -> 0 | H15: =IF(H3<$C$25,0,-H27) -> -1073252.1 | I15: =IF(I3<$C$25,0,-I27) -> -858601.71 | J15: =IF(J3<$C$25,0,-J27) -> -643951.28 | K15: =IF(K3<$C$25,0,-K27) -> -429300.86 | L15: =IF(L3<$C$25,0,-L27) -> -214650.43 | M15: =IF(M3<$C$25,0,-M27) -> -1.847744e-10 | ... Z15: =IF(Z3<$C$25,0,-Z27) -> -1.847744e-10
B16: Saldo Final | F16: =SUM(F11:F15) -> 14716800 | G16: =SUM(G11:G15) -> 15721467 | H16: =SUM(H11:H15) -> 12577174 | I16: =SUM(I11:I15) -> 9432880.1 | J16: =SUM(J11:J15) -> 6288586.8 | K16: =SUM(K11:K15) -> 3144293.4 | L16: =SUM(L11:L15) -> 2.7066562e-09 | M16: =SUM(M11:M15) -> 2.7066562e-09 | ... Z16: =SUM(Z11:Z15) -> 2.7066562e-09
B18: Dívida
B20: Adição | C20: =Premissas!C64 -> 0.7 | D20: CAPEX | F20: =$C$20*Investimentos!F17 -> 14000000 | G20: =$C$20*Investimentos!G17 -> 0 | H20: =$C$20*Investimentos!H17 -> 0 | I20: =$C$20*Investimentos!I17 -> 0 | J20: =$C$20*Investimentos!J17 -> 0 | K20: =$C$20*Investimentos!K17 -> 0 | L20: =$C$20*Investimentos!L17 -> 0 | M20: =$C$20*Investimentos!M17 -> 0 | ... Z20: =$C$20*Investimentos!Z17 -> 0
B22: Vigência | C22: =Premissas!C65 -> 7
B23: Carência principal | C23: =Premissas!C66 -> 2
B24: Amortização | C24: =C22-C23 -> 5 | F24: =IFERROR(-SUM(OFFSET(F20,0,-$C$23,,-MIN(F3-$F$3,$C$24)))/$C$24,0)+IFERROR(-SUM(OFFSET(G31,0,-$C$23,,-MIN(F3-$F$3,$C$24)))/$C$24,0) -> 0 | G24: =IFERROR(-SUM(OFFSET(G20,0,-$C$23,,-MIN(G3-$F$3,$C$24)))/$C$24,0)+IFERROR(-SUM(OFFSET(H31,0,-$C$23,,-MIN(G3-$F$3,$C$24)))/$C$24,0) -> 0 | H24: =IFERROR(-SUM(OFFSET(H20,0,-$C$23,,-MIN(H3-$F$3,$C$24)))/$C$24,0)+IFERROR(-SUM(OFFSET(I31,0,-$C$23,,-MIN(H3-$F$3,$C$24)))/$C$24,0) -> -3144293.4 | I24: =IFERROR(-SUM(OFFSET(I20,0,-$C$23,,-MIN(I3-$F$3,$C$24)))/$C$24,0)+IFERROR(-SUM(OFFSET(J31,0,-$C$23,,-MIN(I3-$F$3,$C$24)))/$C$24,0) -> -3144293.4 | J24: =IFERROR(-SUM(OFFSET(J20,0,-$C$23,,-MIN(J3-$F$3,$C$24)))/$C$24,0)+IFERROR(-SUM(OFFSET(K31,0,-$C$23,,-MIN(J3-$F$3,$C$24)))/$C$24,0) -> -3144293.4 | K24: =IFERROR(-SUM(OFFSET(K20,0,-$C$23,,-MIN(K3-$F$3,$C$24)))/$C$24,0)+IFERROR(-SUM(OFFSET(L31,0,-$C$23,,-MIN(K3-$F$3,$C$24)))/$C$24,0) -> -3144293.4 | L24: =IFERROR(-SUM(OFFSET(L20,0,-$C$23,,-MIN(L3-$F$3,$C$24)))/$C$24,0)+IFERROR(-SUM(OFFSET(M31,0,-$C$23,,-MIN(L3-$F$3,$C$24)))/$C$24,0) -> -3144293.4 | M24: =IFERROR(-SUM(OFFSET(M20,0,-$C$23,,-MIN(M3-$F$3,$C$24)))/$C$24,0)+IFERROR(-SUM(OFFSET(N31,0,-$C$23,,-MIN(M3-$F$3,$C$24)))/$C$24,0) -> 0 | ... Z24: =IFERROR(-SUM(OFFSET(Z20,0,-$C$23,,-MIN(Z3-$F$3,$C$24)))/$C$24,0)+IFERROR(-SUM(OFFSET(AA31,0,-$C$23,,-MIN(Z3-$F$3,$C$24)))/$C$24,0) -> 0
B25: Carência juros | C25: =Premissas!C68 -> 2
B27: Juros | C27: =((1+C28)*(1+C29))-1 -> 0.1024 | F27: =AVERAGE(E16,F11:F12)*$C27 -> 716800 | G27: =AVERAGE(F16,G11:G12)*$C27 -> 1004666.9 | H27: =AVERAGE(G16,H11:H12)*$C27 -> 1073252.1 | I27: =AVERAGE(H16,I11:I12)*$C27 -> 858601.71 | J27: =AVERAGE(I16,J11:J12)*$C27 -> 643951.28 | K27: =AVERAGE(J16,K11:K12)*$C27 -> 429300.86 | L27: =AVERAGE(K16,L11:L12)*$C27 -> 214650.43 | M27: =AVERAGE(L16,M11:M12)*$C27 -> 1.847744e-10 | ... Z27: =AVERAGE(Y16,Z11:Z12)*$C27 -> 1.847744e-10
B28: IPCA | C28: =Premissas!C70 -> 0.04
B29: Spread | C29: =Premissas!C71 -> 0.06
B31: Juros Incorridos na carência | F31: =IF(F3=$C$25-1,SUM($F$27:F27),IF(OR(F3<$C$25,F3>=$C$25),0)) -> 0 | G31: =IF(G3=$C$25-1,SUM($F$27:G27),IF(OR(G3<$C$25,G3>=$C$25),0)) -> 1721466.9 | H31: =IF(H3=$C$25-1,SUM($F$27:H27),IF(OR(H3<$C$25,H3>=$C$25),0)) -> 0 | I31: =IF(I3=$C$25-1,SUM($F$27:I27),IF(OR(I3<$C$25,I3>=$C$25),0)) -> 0 | J31: =IF(J3=$C$25-1,SUM($F$27:J27),IF(OR(J3<$C$25,J3>=$C$25),0)) -> 0 | K31: =IF(K3=$C$25-1,SUM($F$27:K27),IF(OR(K3<$C$25,K3>=$C$25),0)) -> 0 | L31: =IF(L3=$C$25-1,SUM($F$27:L27),IF(OR(L3<$C$25,L3>=$C$25),0)) -> 0 | M31: =IF(M3=$C$25-1,SUM($F$27:M27),IF(OR(M3<$C$25,M3>=$C$25),0)) -> 0 | ... Z31: =IF(Z3=$C$25-1,SUM($F$27:Z27),IF(OR(Z3<$C$25,Z3>=$C$25),0)) -> 0

Sheet Capital de Giro
F3: 0 | G3: =F3+1 -> 1 | H3: =G3+1 -> 2 | I3: =H3+1 -> 3 | J3: =I3+1 -> 4 | K3: =J3+1 -> 5 | L3: =K3+1 -> 6 | M3: =L3+1 -> 7 | N3: =M3+1 -> 8 | ... Z3: =Y3+1 -> 20
B5: Dias/ano | C5: =Premissas!$C$4 -> 365 | F5: =$C$5 -> 365 | G5: =$C$5 -> 365 | H5: =$C$5 -> 365 | I5: =$C$5 -> 365 | J5: =$C$5 -> 365 | K5: =$C$5 -> 365 | L5: =$C$5 -> 365 | M5: =$C$5 -> 365 | ... Z5: =$C$5 -> 365
B6: Inflação | C6: =Premissas!C5 -> 0.04 | F6: =(1+$C$6)^F3 -> 1 | G6: =(1+$C$6)^G3 -> 1.04 | H6: =(1+$C$6)^H3 -> 1.0816 | I6: =(1+$C$6)^I3 -> 1.124864 | J6: =(1+$C$6)^J3 -> 1.1698586 | K6: =(1+$C$6)^K3 -> 1.2166529 | L6: =(1+$C$6)^L3 -> 1.265319 | M6: =(1+$C$6)^M3 -> 1.3159318 | ... Z6: =(1+$C$6)^Z3 -> 2.1911231
B8: Capital de Giro | F8: =+F11+F12-F13 -> 0
B10: Saldo | F10: =+F11+F12-F13 -> 0 | G10: =+G11+G12-G13 -> 285643.84 | H10: =+H11+H12-H13 -> 311589.7 | I10: =+I11+I12-I13 -> 339909.25 | J10: =+J11+J12-J13 -> 370820.32 | K10: =+K11+K12-K13 -> 404560.8 | L10: =+L11+L12-L13 -> 441390.4 | M10: =+M11+M12-M13 -> 481592.72 | ... Z10: =+Z11+Z12-Z13 -> 1500115.7
B11: Contas a Receber | F11: =+F19 -> 0 | G11: =+G19 -> 239342.47 | H11: =+H19 -> 261361.97 | I11: =+I19 -> 285407.27 | J11: =+J19 -> 311664.74 | K11: =+K19 -> 340337.9 | L11: =+L19 -> 371648.99 | M11: =+M19 -> 405840.69 | ... Z11: =+Z19 -> 1274236.1
B12: Estoque | F12: =+F24 -> 0 | G12: =+G24 -> 120668.49 | H12: =+H24 -> 128399.25 | I12: =+I24 -> 136706.42 | J12: =+J24 -> 145637.62 | K12: =+K24 -> 155244.65 | L12: =+L24 -> 165583.87 | M12: =+M24 -> 176716.57 | ... Z12: =+Z24 -> 433891.75
B13: Contas a Pagar | F13: =+F29 -> 0 | G13: =+G29 -> 74367.123 | H13: =+H29 -> 78171.529 | I13: =+I29 -> 82204.445 | J13: =+J29 -> 86482.034 | K13: =+K29 -> 91021.754 | L13: =+L29 -> 95842.462 | M13: =+M29 -> 100964.54 | ... Z13: =+Z29 -> 208012.15
B14: Var. Capital de Giro | F14: =-F10+E10 -> 0 | G14: =-G10+F10 -> -285643.84 | H14: =-H10+G10 -> -25945.863 | I14: =-I10+H10 -> -28319.548 | J14: =-J10+I10 -> -30911.078 | K14: =-K10+J10 -> -33740.474 | L14: =-L10+K10 -> -36829.598 | M14: =-M10+L10 -> -40202.321 | ... Z14: =-Z10+Y10 -> -125764.92
B16: Contas a Receber
B18: Receita Bruta | F18: =DRE!F27 -> 0 | G18: =DRE!G27 -> 17472000 | H18: =DRE!H27 -> 19079424 | I18: =DRE!I27 -> 20834731 | J18: =DRE!J27 -> 22751526 | K18: =DRE!K27 -> 24844667 | L18: =DRE!L27 -> 27130376 | M18: =DRE!M27 -> 29626371 | ... Z18: =DRE!Z27 -> 93019232
B19: PMR | C19: 5 | F19: =F18/F$5*$C19 -> 0 | G19: =G18/G$5*$C19 -> 239342.47 | H19: =H18/H$5*$C19 -> 261361.97 | I19: =I18/I$5*$C19 -> 285407.27 | J19: =J18/J$5*$C19 -> 311664.74 | K19: =K18/K$5*$C19 -> 340337.9 | L19: =L18/L$5*$C19 -> 371648.99 | M19: =M18/M$5*$C19 -> 405840.69 | ... Z19: =Z18/Z$5*$C19 -> 1274236.1
B21: Estoque
B23: CPV | F23: =-DRE!F43 -> 0 | G23: =-DRE!G43 -> 6292000 | H23: =-DRE!H43 -> 6695104 | I23: =-DRE!I43 -> 7128263.2 | J23: =-DRE!J43 -> 7593961.4 | K23: =-DRE!K43 -> 8094899.7 | L23: =-DRE!L43 -> 8634016.1 | M23: =-DRE!M43 -> 9214506.7 | ... Z23: =-DRE!Z43 -> 22624356
B24: PME | C24: 7 | F24: =F23/F$5*$C24 -> 0 | G24: =G23/G$5*$C24 -> 120668.49 | H24: =H23/H$5*$C24 -> 128399.25 | I24: =I23/I$5*$C24 -> 136706.42 | J24: =J23/J$5*$C24 -> 145637.62 | K24: =K23/K$5*$C24 -> 155244.65 | L24: =L23/L$5*$C24 -> 165583.87 | M24: =M23/M$5*$C24 -> 176716.57 | ... Z24: =Z23/Z$5*$C24 -> 433891.75
B26: Contas a Pagar
B28: CPV & Despesas | F28: =-DRE!F43-DRE!F60 -> 0 | G28: =-DRE!G43-DRE!G60 -> 13572000 | H28: =-DRE!H43-DRE!H60 -> 14266304 | I28: =-DRE!I43-DRE!I60 -> 15002311 | J28: =-DRE!J43-DRE!J60 -> 15782971 | K28: =-DRE!K43-DRE!K60 -> 16611470 | L28: =-DRE!L43-DRE!L60 -> 17491249 | M28: =-DRE!M43-DRE!M60 -> 18426029 | ... Z28: =-DRE!Z43-DRE!Z60 -> 37962218
B29: PMP | C29: 2 | F29: =F28/F$5*$C29 -> 0 | G29: =G28/G$5*$C29 -> 74367.123 | H29: =H28/H$5*$C29 -> 78171.529 | I29: =I28/I$5*$C29 -> 82204.445 | J29: =J28/J$5*$C29 -> 86482.034 | K29: =K28/K$5*$C29 -> 91021.754 | L29: =L28/L$5*$C29 -> 95842.462 | M29: =M28/M$5*$C29 -> 100964.54 | ... Z29: =Z28/Z$5*$C29 -> 208012.15
